mcp_sentry/__init__.py
mcp_sentry/__main__.py
mcp_sentry/server.py
iflow_mcp_mcp_100_mcp_sentry-0.6.8.dist-info/METADATA
iflow_mcp_mcp_100_mcp_sentry-0.6.8.dist-info/WHEEL
iflow_mcp_mcp_100_mcp_sentry-0.6.8.dist-info/entry_points.txt
iflow_mcp_mcp_100_mcp_sentry-0.6.8.dist-info/top_level.txt
iflow_mcp_mcp_100_mcp_sentry-0.6.8.dist-info/RECORD
